loser/__init__.py
loser/helpers.py
loser/solution.py
loser/dashboard/__init__.py
loser/dashboard/app.py
loser/dashboard/pipeline.py
loser-0.1.2.dist-info/METADATA
loser-0.1.2.dist-info/WHEEL
loser-0.1.2.dist-info/licenses/LICENSE
loser-0.1.2.dist-info/RECORD
