Metadata-Version: 2.4
Name: loser
Version: 0.1.2
Summary: Local Search for Reference genome selection
Project-URL: Repository, https://github.com/JaspervB-tud/LoSeR
Project-URL: Changelog, https://github.com/JaspervB-tud/LoSeR/blob/main/CHANGELOG.md
Author-email: Jasper van Bemmelen <jaspervanbemmelen@hotmail.com>
License: MIT License
License-File: LICENSE
Classifier: License :: OSI Approved :: MIT License
Classifier: Operating System :: OS Independent
Classifier: Programming Language :: Python :: 3
Classifier: Programming Language :: Python :: 3 :: Only
Requires-Python: >=3.10
Requires-Dist: numpy<3.0,>=2.0
Requires-Dist: scipy<2.0,>=1.14
Provides-Extra: dashboard
Requires-Dist: biopython<2.0,>=1.83; extra == 'dashboard'
Requires-Dist: sourmash<5.0,>=4.8; extra == 'dashboard'
Requires-Dist: streamlit<2.0,>=1.37; extra == 'dashboard'
Provides-Extra: test
Requires-Dist: pytest<9,>=8; extra == 'test'
